pydaffodil/__init__.py
pydaffodil/core.py
pydaffodil-1.2.0.dist-info/licenses/LICENSE
pydaffodil-1.2.0.dist-info/METADATA
pydaffodil-1.2.0.dist-info/WHEEL
pydaffodil-1.2.0.dist-info/top_level.txt
pydaffodil-1.2.0.dist-info/RECORD
