Metadata-Version: 2.4
Name: pydaffodil
Version: 1.2.0
Summary: A cross-platform Python deployment framework for automated remote server deployments via SSH
Home-page: https://github.com/marcuwynu23/pydaffodil
Author: Mark Wayne Menorca
Author-email: marcuwynu23@gmail.com
License: MIT
Project-URL: Bug Reports, https://github.com/marcuwynu23/pydaffodil/issues
Project-URL: Source, https://github.com/marcuwynu23/pydaffodil
Project-URL: Documentation, https://github.com/marcuwynu23/pydaffodil#readme
Keywords: deployment,ssh,scp,remote,server,automation,devops,ci-cd,deploy,vps,remote-deployment,ssh-deployment,python-deployment,cross-platform,file-transfer,remote-execution
Classifier: Development Status :: 4 - Beta
Classifier: Intended Audience :: Developers
Classifier: Intended Audience :: System Administrators
Classifier: Topic :: Software Development :: Libraries :: Python Modules
Classifier: Topic :: System :: Systems Administration
Classifier: Topic :: System :: Installation/Setup
Classifier: Topic :: Internet :: File Transfer Protocol (FTP)
Classifier: Topic :: System :: Archiving :: Packaging
Classifier: Programming Language :: Python :: 3
Classifier: Programming Language :: Python :: 3.6
Classifier: Programming Language :: Python :: 3.7
Classifier: Programming Language :: Python :: 3.8
Classifier: Programming Language :: Python :: 3.9
Classifier: Programming Language :: Python :: 3.10
Classifier: Programming Language :: Python :: 3.11
Classifier: Programming Language :: Python :: 3.12
Classifier: Operating System :: OS Independent
Classifier: Operating System :: Microsoft :: Windows
Classifier: Operating System :: MacOS
Classifier: Operating System :: POSIX :: Linux
Classifier: Environment :: Console
Requires-Python: >=3.6
License-File: LICENSE
Requires-Dist: paramiko>=2.0.0
Requires-Dist: tqdm>=4.60.0
Requires-Dist: colorama>=0.4.0
Dynamic: author
Dynamic: author-email
Dynamic: classifier
Dynamic: description
Dynamic: description-content-type
Dynamic: home-page
Dynamic: keywords
Dynamic: license
Dynamic: license-file
Dynamic: project-url
Dynamic: requires-dist
Dynamic: requires-python
Dynamic: summary
